<forecast seriesName="Varicella">
  <vaccine vaccineName="Single" vaccineIds="178"/>
  <vaccine vaccineName="Combo" vaccineIds="159, 1560"/>
  <vaccine vaccineName="Live" vaccineIds="158, 159, 1560, 160, 161, 162, 171, 175, 178, 180, 2020, 1990, 148"/>
  <schedule scheduleName="P1" dose="1" indication="NO-VAR-HIS" label="1 year">
    <valid age="12 months" interval="" grace="4 days"/>
    <early age="" interval="" grace=""/>
    <due age="12 months" interval="" grace=""/>
    <overdue age="16 months" interval="" grace=""/>
    <finished age="65 years" interval="" grace=""/>
    <after-invalid interval="12 weeks" grace="8 weeks"/>
    <after-contra interval="4 weeks" grace=""/>
    <before-previous interval=""/>
    <indicate vaccineName="Single" schedule="P2" age="13 years" reason=""/>
    <indicate vaccineName="Single" schedule="A2" age="" reason=""/>
    <indicate vaccineName="Combo" schedule="P2" age="13 years" reason=""/>
    <indicate vaccineName="Live" schedule="CONTRA" age="" reason=""/>
    <indicate vaccineName="Combo" schedule="INVALID" age="" reason="MMRV should not be administered to persons 13 years of age or older."/>
  </schedule>
  <schedule scheduleName="P2" dose="2" indication="" label="4 years">
    <valid age="15 months" interval="12 weeks" grace="8 weeks"/>
    <early age="" interval="" grace=""/>
    <due age="4 years" interval="" grace=""/>
    <overdue age="7 years" interval="" grace=""/>
    <finished age="65 years" interval="" grace=""/>
    <after-invalid interval="12 weeks" grace="8 weeks"/>
    <after-contra interval="4 weeks" grace=""/>
    <before-previous interval=""/>
    <indicate vaccineName="Single" schedule="COMPLETE" age="" reason=""/>
    <indicate vaccineName="Combo" schedule="COMPLETE" age="13 years" reason=""/>
    <indicate vaccineName="Live" schedule="CONTRA" age="" reason=""/>
    <indicate vaccineName="Combo" schedule="INVALID" age="" reason="MMRV should not be administered to persons 13 years of age or older."/>
  </schedule>
  <schedule scheduleName="A2" dose="2" indication="" label="13 years +">
    <valid age="13 years" interval="4 weeks" grace="4 days"/>
    <early age="" interval="" grace=""/>
    <due age="13 years" interval="" grace=""/>
    <overdue age="13 years" interval="" grace=""/>
    <finished age="65 years" interval="" grace=""/>
    <after-invalid interval="4 weeks" grace="4 days"/>
    <after-contra interval="4 weeks" grace=""/>
    <before-previous interval=""/>
    <indicate vaccineName="Single" schedule="COMPLETE" age="" reason=""/>
    <indicate vaccineName="Live" schedule="CONTRA" age="" reason=""/>
    <indicate vaccineName="Combo" schedule="INVALID" age="" reason="MMRV should not be administered to persons 13 years of age or older."/>
  </schedule>
</forecast>
